[
  {
    "full_name": "mattermost/mattermost",
    "stargazers_count": 33456,
    "open_issues_count": 958,
    "forks_count": 7938
  },
  {
    "full_name": "pterm/pterm",
    "stargazers_count": 5221,
    "open_issues_count": 66,
    "forks_count": 210
  },
  {
    "full_name": "libp2p/go-libp2p",
    "stargazers_count": 6504,
    "open_issues_count": 291,
    "forks_count": 1181
  },
  {
    "full_name": "AppFlowy-IO/AppFlowy",
    "stargazers_count": 65097,
    "open_issues_count": 1011,
    "forks_count": 4514
  },
  {
    "full_name": "open-sauced/open-sauced",
    "stargazers_count": 954,
    "open_issues_count": 0,
    "forks_count": 1150
  }
]